{"nodes": [{"id": "docs_learning_09_tanstack_query_tanstack_query", "label": "TanStack Query", "file_type": "concept", "source_file": "docs/learning/09-tanstack-query.md", "source_location": null, "source_url": null, "captured_at": null, "author": null, "contributor": null}, {"id": "docs_learning_09_tanstack_query_useeffect_fetch_antipattern", "label": "useEffect + fetch anti-pattern", "file_type": "rationale", "source_file": "docs/learning/09-tanstack-query.md", "source_location": null, "source_url": null, "captured_at": null, "author": null, "contributor": null}, {"id": "docs_learning_09_tanstack_query_usequery", "label": "useQuery hook", "file_type": "code", "source_file": "docs/learning/09-tanstack-query.md", "source_location": null, "source_url": null, "captured_at": null, "author": null, "contributor": null}, {"id": "docs_learning_09_tanstack_query_usemutation", "label": "useMutation hook", "file_type": "code", "source_file": "docs/learning/09-tanstack-query.md", "source_location": null, "source_url": null, "captured_at": null, "author": null, "contributor": null}, {"id": "docs_learning_09_tanstack_query_querykey", "label": "queryKey pattern", "file_type": "concept", "source_file": "docs/learning/09-tanstack-query.md", "source_location": null, "source_url": null, "captured_at": null, "author": null, "contributor": null}, {"id": "docs_learning_09_tanstack_query_invalidatequeries", "label": "queryClient.invalidateQueries", "file_type": "code", "source_file": "docs/learning/09-tanstack-query.md", "source_location": null, "source_url": null, "captured_at": null, "author": null, "contributor": null}], "edges": [{"source": "docs_learning_09_tanstack_query_useeffect_fetch_antipattern", "target": "docs_learning_09_tanstack_query_tanstack_query", "relation": "rationale_for", "confidence": "EXTRACTED", "confidence_score": 1.0, "source_file": "docs/learning/09-tanstack-query.md", "source_location": null, "weight": 1.0}, {"source": "docs_learning_09_tanstack_query_tanstack_query", "target": "docs_learning_09_tanstack_query_usequery", "relation": "implements", "confidence": "EXTRACTED", "confidence_score": 1.0, "source_file": "docs/learning/09-tanstack-query.md", "source_location": null, "weight": 1.0}, {"source": "docs_learning_09_tanstack_query_tanstack_query", "target": "docs_learning_09_tanstack_query_usemutation", "relation": "implements", "confidence": "EXTRACTED", "confidence_score": 1.0, "source_file": "docs/learning/09-tanstack-query.md", "source_location": null, "weight": 1.0}, {"source": "docs_learning_09_tanstack_query_usequery", "target": "docs_learning_09_tanstack_query_querykey", "relation": "shares_data_with", "confidence": "EXTRACTED", "confidence_score": 1.0, "source_file": "docs/learning/09-tanstack-query.md", "source_location": null, "weight": 1.0}, {"source": "docs_learning_09_tanstack_query_usemutation", "target": "docs_learning_09_tanstack_query_invalidatequeries", "relation": "calls", "confidence": "EXTRACTED", "confidence_score": 1.0, "source_file": "docs/learning/09-tanstack-query.md", "source_location": null, "weight": 1.0}], "hyperedges": []}